schul_cloud_resources_api_v1/__init__.py
schul_cloud_resources_api_v1/api_client.py
schul_cloud_resources_api_v1/auth.py
schul_cloud_resources_api_v1/configuration.py
schul_cloud_resources_api_v1/fixes.py
schul_cloud_resources_api_v1/rest.py
schul_cloud_resources_api_v1/apis/__init__.py
schul_cloud_resources_api_v1/apis/resource_api.py
schul_cloud_resources_api_v1/models/__init__.py
schul_cloud_resources_api_v1/models/error_element.py
schul_cloud_resources_api_v1/models/error_response.py
schul_cloud_resources_api_v1/models/jsonapi.py
schul_cloud_resources_api_v1/models/jsonapi_meta.py
schul_cloud_resources_api_v1/models/resource.py
schul_cloud_resources_api_v1/models/resource_ids_response.py
schul_cloud_resources_api_v1/models/resource_ids_response_data.py
schul_cloud_resources_api_v1/models/resource_ids_response_links.py
schul_cloud_resources_api_v1/models/resource_post.py
schul_cloud_resources_api_v1/models/resource_post_data.py
schul_cloud_resources_api_v1/models/resource_response.py
schul_cloud_resources_api_v1/models/resource_response_data.py
schul_cloud_resources_api_v1/models/resource_response_links.py
schul_cloud_resources_api_v1/models/resource_type.py
schul_cloud_resources_api_v1/schema/__init__.py
schul_cloud_resources_api_v1/schema/json/error/error.json
schul_cloud_resources_api_v1/schema/json/error/examples/invalid/code-and-title-not-matching.json
schul_cloud_resources_api_v1/schema/json/error/examples/invalid/invalid-jsonapi.json
schul_cloud_resources_api_v1/schema/json/error/examples/invalid/missing-detail.json
schul_cloud_resources_api_v1/schema/json/error/examples/invalid/missing-status.json
schul_cloud_resources_api_v1/schema/json/error/examples/invalid/missing-title.json
schul_cloud_resources_api_v1/schema/json/error/examples/invalid/no-error.json
schul_cloud_resources_api_v1/schema/json/error/examples/invalid/wrong-title.json
schul_cloud_resources_api_v1/schema/json/error/examples/valid/404.json
schul_cloud_resources_api_v1-1.0.0.326.dist-info/DESCRIPTION.rst
schul_cloud_resources_api_v1-1.0.0.326.dist-info/METADATA
schul_cloud_resources_api_v1-1.0.0.326.dist-info/RECORD
schul_cloud_resources_api_v1-1.0.0.326.dist-info/WHEEL
schul_cloud_resources_api_v1-1.0.0.326.dist-info/metadata.json
schul_cloud_resources_api_v1-1.0.0.326.dist-info/top_level.txt
